download_files_by_map/__init__.py
download_files_by_map/cli.py
download_files_by_map/download_files_by_map.py
download_files_by_map/util.py
download_files_by_map-0.3.0.dist-info/METADATA
download_files_by_map-0.3.0.dist-info/WHEEL
download_files_by_map-0.3.0.dist-info/entry_points.txt
download_files_by_map-0.3.0.dist-info/licenses/LICENSE
download_files_by_map-0.3.0.dist-info/RECORD
