Metadata-Version: 2.4
Name: download_files_by_map
Version: 0.3.0
Summary: download files using a json tree map
License: MIT
License-File: LICENSE
Keywords: downloader
Author: Siak Hooi
Author-email: siakhooi@gmail.com
Requires-Python: >=3.10
Classifier: Development Status :: 4 - Beta
Classifier: Environment :: Console
Classifier: License :: OSI Approved :: MIT License
Classifier: Topic :: Utilities
Requires-Dist: requests (>=2.32.3,<3.0.0)
Project-URL: Bug Tracker, https://github.com/siakhooi/python-download-files-by-map/issues
Project-URL: Documentation, https://github.com/siakhooi/python-download-files-by-map/wiki
Project-URL: Homepage, https://github.com/siakhooi/python-download-files-by-map
Project-URL: Repository, https://github.com/siakhooi/python-download-files-by-map
